fsspec_notion/__init__.py
fsspec_notion/notionfs.py
fsspec_notion/py.typed
fsspec_notion-0.0.1.dist-info/METADATA
fsspec_notion-0.0.1.dist-info/WHEEL
fsspec_notion-0.0.1.dist-info/licenses/LICENSE
fsspec_notion-0.0.1.dist-info/RECORD
