Metadata-Version: 2.3
Name: fsspec-notion
Version: 0.0.1
Summary: fsspec backend for notion workspaces (notion.so)
Project-URL: Documentation, https://phil65.github.io/fsspec-notion/
Project-URL: Source, https://github.com/phil65/fsspec-notion
Author-email: Philipp Temminghoff <philipptemminghoff@gmail.com>
License-Expression: MIT
License-File: LICENSE
Classifier: Development Status :: 4 - Beta
Classifier: Intended Audience :: Developers
Classifier: Operating System :: OS Independent
Classifier: Programming Language :: Python :: 3
Classifier: Programming Language :: Python :: 3 :: Only
Classifier: Programming Language :: Python :: 3.12
Classifier: Programming Language :: Python :: 3.13
Classifier: Programming Language :: Python :: 3.14
Classifier: Topic :: Documentation
Classifier: Topic :: Software Development
Classifier: Topic :: Utilities
Classifier: Typing :: Typed
Requires-Python: >=3.12
Requires-Dist: fsspec
Requires-Dist: notion-client
